odoo/addons/account_bank_statement_import_online/README.rst
odoo/addons/account_bank_statement_import_online/__init__.py
odoo/addons/account_bank_statement_import_online/__manifest__.py
odoo/addons/account_bank_statement_import_online/data/account_bank_statement_import_online.xml
odoo/addons/account_bank_statement_import_online/i18n/account_bank_statement_import_online.pot
odoo/addons/account_bank_statement_import_online/i18n/nl.po
odoo/addons/account_bank_statement_import_online/models/__init__.py
odoo/addons/account_bank_statement_import_online/models/account_journal.py
odoo/addons/account_bank_statement_import_online/models/online_bank_statement_provider.py
odoo/addons/account_bank_statement_import_online/readme/CONFIGURE.rst
odoo/addons/account_bank_statement_import_online/readme/CONTRIBUTORS.rst
odoo/addons/account_bank_statement_import_online/readme/DESCRIPTION.rst
odoo/addons/account_bank_statement_import_online/readme/USAGE.rst
odoo/addons/account_bank_statement_import_online/security/ir.model.access.csv
odoo/addons/account_bank_statement_import_online/security/online_bank_statement_provider.xml
odoo/addons/account_bank_statement_import_online/static/description/icon.png
odoo/addons/account_bank_statement_import_online/static/description/index.html
odoo/addons/account_bank_statement_import_online/tests/__init__.py
odoo/addons/account_bank_statement_import_online/tests/online_bank_statement_provider_dummy.py
odoo/addons/account_bank_statement_import_online/tests/test_account_bank_statement_import_online.py
odoo/addons/account_bank_statement_import_online/views/account_journal.xml
odoo/addons/account_bank_statement_import_online/views/online_bank_statement_provider.xml
odoo/addons/account_bank_statement_import_online/wizards/__init__.py
odoo/addons/account_bank_statement_import_online/wizards/online_bank_statement_pull_wizard.py
odoo/addons/account_bank_statement_import_online/wizards/online_bank_statement_pull_wizard.xml
odoo12_addon_account_bank_statement_import_online-12.0.2.0.0.dist-info/METADATA
odoo12_addon_account_bank_statement_import_online-12.0.2.0.0.dist-info/WHEEL
odoo12_addon_account_bank_statement_import_online-12.0.2.0.0.dist-info/top_level.txt
odoo12_addon_account_bank_statement_import_online-12.0.2.0.0.dist-info/RECORD
