Metadata-Version: 2.1
Name: odoo12-addon-account-bank-statement-import-online
Version: 12.0.2.0.0
Summary: Online bank statements update
Home-page: https://github.com/OCA/bank-statement-import
Author: CorporateHub, Odoo Community Association (OCA)
Author-email: support@odoo-community.org
License: AGPL-3
Platform: UNKNOWN
Classifier: Programming Language :: Python
Classifier: Framework :: Odoo
Classifier: Framework :: Odoo :: 12.0
Classifier: License :: OSI Approved :: GNU Affero General Public License v3
Requires-Python: >=3.5
Requires-Dist: odoo12-addon-web-widget-dropdown-dynamic
Requires-Dist: odoo (<12.1dev,>=12.0a)
